Metadata-Version: 2.4
Name: uhg
Version: 0.3.7
Summary: Universal Hyperbolic Geometry Library for Machine Learning
Home-page: https://github.com/zbovaird/UHG-Library
Author: UHG Library Team
Author-email: info@uhglibrary.org
License: MIT
Project-URL: Bug Tracker, https://github.com/zbovaird/UHG-Library/issues
Project-URL: Source Code, https://github.com/zbovaird/UHG-Library
Project-URL: Documentation, https://github.com/zbovaird/UHG-Library/tree/main/docs
Classifier: Development Status :: 3 - Alpha
Classifier: Intended Audience :: Science/Research
Classifier: License :: OSI Approved :: MIT License
Classifier: Programming Language :: Python :: 3.8
Classifier: Programming Language :: Python :: 3.9
Classifier: Topic :: Scientific/Engineering :: Mathematics
Classifier: Topic :: Scientific/Engineering :: Artificial Intelligence
Requires-Python: >=3.8
Requires-Dist: numpy>=1.19.0
Requires-Dist: scipy>=1.6.0
Requires-Dist: networkx>=2.5
Requires-Dist: pytest>=6.0.0
Requires-Dist: matplotlib>=3.3.0
Requires-Dist: tqdm>=4.50.0
Provides-Extra: torch
Requires-Dist: torch>=1.8.0; extra == "torch"
Provides-Extra: dev
Requires-Dist: black; extra == "dev"
Requires-Dist: flake8; extra == "dev"
Requires-Dist: mypy; extra == "dev"
Requires-Dist: pytest-cov; extra == "dev"
Dynamic: author
Dynamic: author-email
Dynamic: classifier
Dynamic: description
Dynamic: description-content-type
Dynamic: home-page
Dynamic: project-url
Dynamic: provides-extra
Dynamic: requires-dist
Dynamic: requires-python
Dynamic: summary
